ExoplanetPy/__init__.py
ExoplanetPy/planet.py
ExoplanetPy/system.py
ExoplanetPy/test_v0.py
ExoplanetPy-0.1.1.dist-info/LICENSE
ExoplanetPy-0.1.1.dist-info/METADATA
ExoplanetPy-0.1.1.dist-info/WHEEL
ExoplanetPy-0.1.1.dist-info/top_level.txt
ExoplanetPy-0.1.1.dist-info/RECORD
