Metadata-Version: 2.1
Name: ExoplanetPy
Version: 0.1.1
Summary: Package for multiple exoplanet system modelling
Home-page: https://github.com/ExoplanetPy/ExoplanetPy
Author: Arnav Das & Devansh Jain
Author-email: arnav257@gmail.com
License: UNKNOWN
Keywords: exoplanets,orbits,visualize,astronomy
Platform: UNKNOWN
Classifier: Development Status :: 2 - Pre-Alpha
Classifier: Intended Audience :: Science/Research
Classifier: License :: OSI Approved :: MIT License
Classifier: Operating System :: OS Independent
Classifier: Programming Language :: Python
Classifier: Programming Language :: Python :: 3 :: Only
Classifier: Programming Language :: Python :: 3.5
Classifier: Programming Language :: Python :: 3.6
Classifier: Programming Language :: Python :: 3.7
Classifier: Programming Language :: Python :: 3.8
Classifier: Programming Language :: Python :: 3.9
Classifier: Programming Language :: Python :: 3.10
Classifier: Topic :: Scientific/Engineering
Classifier: Topic :: Scientific/Engineering :: Astronomy
Classifier: Topic :: Scientific/Engineering :: Visualization
Requires-Python: >=3.5, <4
Requires-Dist: numpy
Requires-Dist: matplotlib
Requires-Dist: scipy
Requires-Dist: seaborn
